fastapi_neon/__init__.py
fastapi_neon/main.py
fastapi_neon/settings.py
fastapi_neon-0.1.0.dist-info/METADATA
fastapi_neon-0.1.0.dist-info/WHEEL
fastapi_neon-0.1.0.dist-info/RECORD
