Metadata-Version: 2.1
Name: fastapi-neon
Version: 0.1.0
Summary: 
Author: Zia Khan
Requires-Python: >=3.12,<4.0
Classifier: Programming Language :: Python :: 3
Classifier: Programming Language :: Python :: 3.12
Requires-Dist: fastapi (>=0.110,<0.111)
Requires-Dist: httpx (>=0.27.0,<0.28.0)
Requires-Dist: psycopg[binary] (>=3.1.18,<4.0.0)
Requires-Dist: pytest (>=8.0.2,<9.0.0)
Requires-Dist: sqlmodel (>=0.0.16,<0.0.17)
Requires-Dist: uvicorn[standard] (>=0.29.0,<0.30.0)
Requires-Dist: verify-email (>=2.4.3,<3.0.0)
